__init__.py
example.py
cornershop_stdlib-0.0.1.dist-info/LICENSE
cornershop_stdlib-0.0.1.dist-info/METADATA
cornershop_stdlib-0.0.1.dist-info/WHEEL
cornershop_stdlib-0.0.1.dist-info/top_level.txt
cornershop_stdlib-0.0.1.dist-info/RECORD
