Metadata-Version: 2.1
Name: cornershop-stdlib
Version: 0.0.1
Summary: A warning package to avoid confusion dependency attacks
Author-email: Leonel De Leon <leonel.deleon@sideralsynchrony.com>
License: Copyright (c) 2018 The Python Packaging Authority        
Project-URL: Homepage, https://sideralsynchrony.com/dependency_attacks.html
Project-URL: Bug Tracker, https://github.com/leinn32/dependencyConfusion/issues
Classifier: Programming Language :: Python :: 3
Classifier: License :: OSI Approved :: MIT License
Classifier: Operating System :: OS Independent
Requires-Python: >=3.8
License-File: LICENSE
